XTool.py
xissue/__init__.py
xissue/xissuer.py
xissue-1.0.0.dist-info/LICENSE.txt
xissue-1.0.0.dist-info/METADATA
xissue-1.0.0.dist-info/WHEEL
xissue-1.0.0.dist-info/top_level.txt
xissue-1.0.0.dist-info/RECORD
