Metadata-Version: 2.1
Name: xissue
Version: 1.0.0
Summary: this is a tools lirary.
Home-page: https://www.juyerhy.com/PythonCode
Author: ivey
Author-email: play2714@sina.cn
License: MIT
Platform: UNKNOWN
